[
  {
    "id": "prop-ava-001",
    "slug": "the-avalon",
    "title": "The Avalon",
    "status": "available",
    "price": 525000,
    "beds": 3,
    "baths": 2,
    "sqft": 1980,
    "city": "Cedar Park",
    "gallery": ["/img/avalon-1.jpg","/img/solstice-1.jpg"],
    "features": ["Open concept", "2-car garage", "Covered patio"],
    "publishedAt": "2025-01-20T00:00:00.000Z"
  },
  {
    "id": "prop-sol-002",
    "slug": "the-solstice",
    "title": "The Solstice",
    "status": "sold",
    "price": 610000,
    "beds": 4,
    "baths": 3,
    "sqft": 2430,
    "city": "Leander",
    "gallery": ["/img/solstice-1.jpg"],
    "features": ["Guest suite", "Chef kitchen"],
    "publishedAt": "2025-03-02T00:00:00.000Z"
  }
]
